Package/__init__.py
Package/outliers.py
outlier_3579-1.0.0.dist-info/LICENSE.txt
outlier_3579-1.0.0.dist-info/METADATA
outlier_3579-1.0.0.dist-info/WHEEL
outlier_3579-1.0.0.dist-info/entry_points.txt
outlier_3579-1.0.0.dist-info/top_level.txt
outlier_3579-1.0.0.dist-info/RECORD
